{
  "url": "https://www.redfin.com/city/1903/FL/Boca-Raton/housing-market",
  "task_id": "c10cf9c3-ce49-4ac4-91d4-2d391c164c29",
  "status": "success",
  "data": {
    "parsing": {
      "name": "Boca Raton Housing Market: House Prices & Trends | Redfin",
      "description": "The Boca Raton, FL housing market is not very competitive, scoring 26 out of 100. The average Boca Raton house price was $813K last month, down 6.1% since last year.",
      "price": "$813K",
      "median_sale_price": "$813K",
      "avg_days_on_market": "86",
      "num_homes_sold": "192",
      "median_sale_per_sqft": "$445",
      "sale_to_list_ratio": "94.8%",
      "yoy_sale_price_change": "-6.1%"
    }
  },
  "metadata": {
    "query_time": "2026-05-10T12:07:39.240Z",
    "query_duration": 9021,
    "response_parameters": {
      "input_url": "https://www.redfin.com/city/1903/FL/Boca-Raton/housing-market"
    },
    "driver": "wsa-6",
    "agent": "redfin_market_housing_data_community_2026_05_02"
  },
  "status_code": 200,
  "warnings": [
    "render_options is ignored because render is false",
    "render is ignored because driver is configured"
  ]
}